cogni_summary/__init__.py
cogni_summary/main.py
cogni_summary/prompts.py
cogni_summary-2025.12.21183907.dist-info/METADATA
cogni_summary-2025.12.21183907.dist-info/WHEEL
cogni_summary-2025.12.21183907.dist-info/top_level.txt
cogni_summary-2025.12.21183907.dist-info/RECORD
