Metadata-Version: 2.4
Name: cogni-summary
Version: 2025.12.21183907
Summary: cogni-summary efficiently generates structured non-technical summaries for productivity and cognitive science content.
Author-email: cogni-summary <hi@eugene.plus>
License: MIT
Project-URL: Homepage, https://github.com/chigwell/cogni-summary
Requires-Python: >=3.9
Requires-Dist: langchain-llm7>=0.0.0
Requires-Dist: llmatch-messages>=0.0.0
Requires-Dist: langchain-core>=0.3.0
